README.md
setup.py
dragon_sword.egg-info/PKG-INFO
dragon_sword.egg-info/SOURCES.txt
dragon_sword.egg-info/dependency_links.txt
dragon_sword.egg-info/top_level.txt
gservices/__init__.py
gservices/cli.py
gservices/decorator.py
gservices/errno.py
gservices/registry_cli.py
gservices/registry_config.py
gservices/registry_pb2.py
gservices/registry_pb2_grpc.py
gservices/registry_server.py
gservices/registry_service.py
gservices/storage_cli.py
gservices/storage_pb2.py
gservices/storage_pb2_grpc.py
gservices/storage_service.py
gservices/storage_utils.py
gservices/user_cli.py
gservices/user_pb2.py
gservices/user_pb2_grpc.py
gservices/user_service.py
gservices/utils.py
test/__init__.py
test/common.py
test/test_file.py
test/test_file_path.py
test/test_flow_limit.py
test/test_registry_service.py
test/test_time.py
test/test_user.py
test/test_user_service.py
test/test_utils_auth_token.py
test/test_utils_log.py
test/test_utils_storage.py
third_party/__init__.py
third_party/errno.py
third_party/tencent_cloud/__init__.py
third_party/tencent_cloud/dnspod.py
third_party/wps/__init__.py
third_party/wps/_client.py
third_party/wps/errno.py
third_party/wps/main.py
third_party/xunfei/__init__.py
third_party/xunfei/iat_ws.py
third_party/xunfei/parse.py
third_party/xunfei/rtasr.py
third_party/youdu/__init__.py
third_party/youdu/main.py
utils/__init__.py
utils/call.py
utils/config.py
utils/errno.py
utils/git.py
utils/pe_tools.py
utils/server_config.py
utils/svn.py
utils/system.py
utils/time.py
utils/auth/__init__.py
utils/auth/auth.py
utils/auth/errno.py
utils/auth/token.py
utils/data/__init__.py
utils/data/asr.py
utils/data/cache.py
utils/data/csv.py
utils/data/data.py
utils/data/hash.py
utils/data/record_csv.py
utils/data/url.py
utils/file/__init__.py
utils/file/_json.py
utils/file/_path.py
utils/file/compress.py
utils/file/filename.py
utils/file/fileop.py
utils/file/lock.py
utils/file/type.py
utils/flow_limit/__init__.py
utils/flow_limit/base.py
utils/flow_limit/dist.py
utils/flow_limit/file.py
utils/flow_limit/mem.py
utils/log/__init__.py
utils/log/conf.py
utils/log/log.py
utils/log/logger.py
utils/log/mp_handler.py
