Metadata-Version: 2.1
Name: dragon-sword
Version: 0.0.12
Summary: common tool.
Home-page: UNKNOWN
Author: wuruimiao
Author-email: dev.wuruimiao@qq.com
License: MIT
Platform: UNKNOWN
Classifier: License :: OSI Approved :: MIT License
Classifier: Programming Language :: Python
Classifier: Programming Language :: Python :: 3
Classifier: Programming Language :: Python :: 3.6
Classifier: Programming Language :: Python :: Implementation :: CPython
Classifier: Programming Language :: Python :: Implementation :: PyPy
Requires-Python: >=3.6.0
